qje5vf/__init__.py
qje5vf/time_value_money.py
qje5vf/tokenize_text.py
qje5vf-0.0.1.dist-info/LICENSE
qje5vf-0.0.1.dist-info/METADATA
qje5vf-0.0.1.dist-info/WHEEL
qje5vf-0.0.1.dist-info/top_level.txt
qje5vf-0.0.1.dist-info/RECORD
