Metadata-Version: 2.1
Name: qje5vf
Version: 0.0.1
Summary: boodle oodle noodle poodle doodle moo
Author-email: Thomas Hammons <qje5vf@virginia.com>
Project-URL: homepage, https://github.com/thammo4/qje5vf_DS5111su24_lab_01
Project-URL: issues, https://github.com/thammo4/qje5vf_DS5111su24_lab_01/issues
Classifier: Programming Language :: Python :: 3
Classifier: License :: OSI Approved :: Apache Software License
Classifier: Operating System :: OS Independent
Requires-Python: >=3.7
License-File: LICENSE
